{"collections": {"abc12345/123": {"vectors": {"size": 1024, "distance": "Cosine", "hnsw_config": null, "quantization_config": null, "on_disk": null, "datatype": null, "multivector_config": null}, "shard_number": null, "sharding_method": null, "replication_factor": null, "write_consistency_factor": null, "on_disk_payload": null, "hnsw_config": null, "wal_config": null, "optimizers_config": null, "init_from": null, "quantization_config": null, "sparse_vectors": null, "strict_mode_config": null}, "abc12345/qwerty4321": {"vectors": {"size": 1024, "distance": "Cosine", "hnsw_config": null, "quantization_config": null, "on_disk": null, "datatype": null, "multivector_config": null}, "shard_number": null, "sharding_method": null, "replication_factor": null, "write_consistency_factor": null, "on_disk_payload": null, "hnsw_config": null, "wal_config": null, "optimizers_config": null, "init_from": null, "quantization_config": null, "sparse_vectors": null, "strict_mode_config": null}, "672bafa0-6db9-4395-854c-afa5ea23f2ea_new123456789": {"vectors": {"size": 1024, "distance": "Cosine", "hnsw_config": null, "quantization_config": null, "on_disk": null, "datatype": null, "multivector_config": null}, "shard_number": null, "sharding_method": null, "replication_factor": null, "write_consistency_factor": null, "on_disk_payload": null, "hnsw_config": null, "wal_config": null, "optimizers_config": null, "init_from": null, "quantization_config": null, "sparse_vectors": null, "strict_mode_config": null}, "f16bede0-9ee2-46d3-bf7c-8e73245c2e47_aaaaaaaaa": {"vectors": {"size": 1024, "distance": "Cosine", "hnsw_config": null, "quantization_config": null, "on_disk": null, "datatype": null, "multivector_config": null}, "shard_number": null, "sharding_method": null, "replication_factor": null, "write_consistency_factor": null, "on_disk_payload": null, "hnsw_config": null, "wal_config": null, "optimizers_config": null, "init_from": null, "quantization_config": null, "sparse_vectors": null, "strict_mode_config": null}}, "aliases": {}}